REMLA_Test_Lib_version
