Metadata-Version: 2.1
Name: REMLA-Test-Lib-version
Version: 0.1.1
Summary: A version-aware library designed to provide robust version management and utility functions
Home-page: UNKNOWN
Author: Nick Dubbeldam
Author-email: nick.dubbeldasm@live.nl
License: UNKNOWN
Platform: UNKNOWN
Classifier: Programming Language :: Python :: 3
Classifier: License :: OSI Approved :: MIT License
Classifier: Operating System :: OS Independent
Requires-Python: >=3.6
License-File: LICENSE
